dashboard/__init__.py
dashboard/admin.py
dashboard/apps.py
dashboard/base.py
dashboard/decorators.py
dashboard/forms.py
dashboard/models.py
dashboard/sites.py
dashboard/tests.py
dashboard/urls.py
dashboard/utils.py
dashboard/views.py
dashboard/migrations/__init__.py
dashboard/static/dashboard/css/dark-theme-core.css
dashboard/static/dashboard/css/forms.css
dashboard/static/dashboard/css/nucleo-icons.css
dashboard/static/dashboard/css/nucleo-svg.css
dashboard/static/dashboard/css/soft-ui-dashboard.css
dashboard/static/dashboard/css/widgets.css
dashboard/static/dashboard/fonts/nucleo-icons.eot
dashboard/static/dashboard/fonts/nucleo-icons.svg
dashboard/static/dashboard/fonts/nucleo-icons.ttf
dashboard/static/dashboard/fonts/nucleo-icons.woff
dashboard/static/dashboard/fonts/nucleo-icons.woff2
dashboard/static/dashboard/fonts/nucleo.eot
dashboard/static/dashboard/fonts/nucleo.ttf
dashboard/static/dashboard/fonts/nucleo.woff
dashboard/static/dashboard/fonts/nucleo.woff2
dashboard/static/dashboard/images/icons/favicon.ico
dashboard/static/dashboard/img/apple-icon.png
dashboard/static/dashboard/img/bg1.jpg
dashboard/static/dashboard/img/bruce-mars.jpg
dashboard/static/dashboard/img/down-arrow-dark.svg
dashboard/static/dashboard/img/down-arrow-white.svg
dashboard/static/dashboard/img/down-arrow.svg
dashboard/static/dashboard/img/favicon.png
dashboard/static/dashboard/img/home-decor-1.jpg
dashboard/static/dashboard/img/home-decor-2.jpg
dashboard/static/dashboard/img/home-decor-3.jpg
dashboard/static/dashboard/img/icon-calendar.svg
dashboard/static/dashboard/img/icon-clock.svg
dashboard/static/dashboard/img/ivana-square.jpg
dashboard/static/dashboard/img/ivancik.jpg
dashboard/static/dashboard/img/kal-visuals-square.jpg
dashboard/static/dashboard/img/logo-ct-dark.png
dashboard/static/dashboard/img/logo-ct.png
dashboard/static/dashboard/img/marie.jpg
dashboard/static/dashboard/img/team-1.jpg
dashboard/static/dashboard/img/team-2.jpg
dashboard/static/dashboard/img/team-3.jpg
django_template_dashboard-0.1.14.dist-info/LICENSE
django_template_dashboard-0.1.14.dist-info/METADATA
django_template_dashboard-0.1.14.dist-info/WHEEL
django_template_dashboard-0.1.14.dist-info/top_level.txt
django_template_dashboard-0.1.14.dist-info/RECORD
