Metadata-Version: 2.1
Name: django-template-dashboard
Version: 0.1.14
Summary: A dashboard based on Django template.
Author-email: Micro Enjoy <fuqiang.work@foxamil.com>
License: Apache License
Project-URL: Homepage, https://github.com/django-libraries/django-template-dashboard
Project-URL: Documentation, https://github.com/django-libraries/django-template-dashboard
Project-URL: IssueTracker, https://github.com/django-libraries/django-template-dashboard/issues
Project-URL: Source, https://github.com/django-libraries/django-template-dashboard
License-File: LICENSE
Requires-Dist: Django >=3.0
